pygita/__init__.py
pygita/chapter.py
pygita/client.py
pygita/constants.py
pygita/exceptions.py
pygita/verse.py
tests/__init__.py
tests/conftest.py
tests/data.py
tests/test_chapter.py
tests/test_verse.py
pygita-2.0.0.dist-info/LICENSE
pygita-2.0.0.dist-info/METADATA
pygita-2.0.0.dist-info/WHEEL
pygita-2.0.0.dist-info/top_level.txt
pygita-2.0.0.dist-info/RECORD
