Metadata-Version: 2.1
Name: pygita
Version: 2.0.0
Summary: pygita is a wrapper
Home-page: https://github.com/TheShubhendra/pygita
Author: Shubhendra Kushwaha
Author-email: shubhendrakushwaha94@gmail.com
License: MIT
Keywords: Gita,ShrimadBhagwatGita,Verse,Literature,Mythology,Hinduism
Platform: UNKNOWN
Classifier: Development Status :: 5 - Production/Stable
Classifier: Environment :: Console
Classifier: Intended Audience :: Developers
Classifier: Intended Audience :: Religion
Classifier: Topic :: Software Development :: Build Tools
Classifier: Topic :: Religion
Classifier: Topic :: Sociology :: History
Classifier: Topic :: Software Development
Classifier: License :: OSI Approved :: MIT License
Classifier: License :: Free For Educational Use
Classifier: License :: Free For Home Use
Classifier: Natural Language :: English
Classifier: Natural Language :: Hindi
Classifier: Programming Language :: Python :: 3
Classifier: Programming Language :: Python :: 3.4
Classifier: Programming Language :: Python :: 3.5
Classifier: Programming Language :: Python :: 3.6
Classifier: Programming Language :: Python :: 3.7
Classifier: Programming Language :: Python :: 3.8
Classifier: Programming Language :: Python :: 3.9
Requires-Python: >=3.0
Requires-Dist: requests
